sdc_core/__init__.py
sdc_core/apps.py
sdc_core/consumers.py
sdc_core/management/__init__.py
sdc_core/management/commands/__init__.py
sdc_core/management/commands/_private.py
sdc_core/management/commands/init_add/__init__.py
sdc_core/management/commands/init_add/add_controller_manager.py
sdc_core/management/commands/init_add/add_model_manager.py
sdc_core/management/commands/init_add/options.py
sdc_core/management/commands/init_add/sdc_core_manager.py
sdc_core/management/commands/init_add/settings_manager.py
sdc_core/management/commands/init_add/utils.py
sdc_core/management/commands/sdc_cc.py
sdc_core/management/commands/sdc_db_tools.py
sdc_core/management/commands/sdc_get_controller_infos.py
sdc_core/management/commands/sdc_get_controller_url.py
sdc_core/management/commands/sdc_get_model_infos.py
sdc_core/management/commands/sdc_init.py
sdc_core/management/commands/sdc_is_installed.py
sdc_core/management/commands/sdc_new_model.py
sdc_core/management/commands/sdc_overwrite_lib_file.py
sdc_core/management/commands/sdc_shell_execute_script.py
sdc_core/management/commands/sdc_update_links.py
sdc_core/management/commands/sdc_update_url.py
sdc_core/management/commands/utils/__init__.py
sdc_core/sdc_extentions/__init__.py
sdc_core/sdc_extentions/forms.py
sdc_core/sdc_extentions/import_manager.py
sdc_core/sdc_extentions/models.py
sdc_core/sdc_extentions/response.py
sdc_core/sdc_extentions/search.py
sdc_core/sdc_extentions/views.py
sdc_core/signals.py
sdc_core/template_files/.devcontainer/Dockerfile
sdc_core/template_files/.devcontainer/devcontainer.json
sdc_core/template_files/.devcontainer/on_create.sh
sdc_core/template_files/.devcontainer/on_startup.sh
sdc_core/template_files/Assets/babel.config.json
sdc_core/template_files/Assets/gulpfile.jsx
sdc_core/template_files/Assets/src/index.organizer.js
sdc_core/template_files/Assets/src/index.style.scss
sdc_core/template_files/Assets/static/img/favicon.png
sdc_core/template_files/Assets/tests/config/post-test-teardown.js
simpledomcontrol-0.57.20.dist-info/METADATA
simpledomcontrol-0.57.20.dist-info/WHEEL
simpledomcontrol-0.57.20.dist-info/RECORD
